blob_descriptor/__init__.py
blob_descriptor/__main__.py
blob_descriptor/assemble.py
blob_descriptor/check.py
blob_descriptor/construct.py
blob_descriptor/create.py
blob_descriptor/descriptor.py
blob_descriptor/finder.py
blob_descriptor/main.py
blob_descriptor/utils.py
blob_descriptor/verify.py
blob_descriptor-0.0.3.dist-info/licenses/LICENSE
blob_descriptor-0.0.3.dist-info/METADATA
blob_descriptor-0.0.3.dist-info/WHEEL
blob_descriptor-0.0.3.dist-info/entry_points.txt
blob_descriptor-0.0.3.dist-info/top_level.txt
blob_descriptor-0.0.3.dist-info/RECORD
