Metadata-Version: 2.4
Name: blob_descriptor
Version: 0.0.3
Summary: Toolkit for managing large binary files through chunking and metadata descriptors
Author: Jet-Logic
License:                     GNU GENERAL PUBLIC LICENSE
Project-URL: Homepage, https://github.com/jet-logic/blob_descriptor
Project-URL: Documentation, https://github.com/jet-logic/blob_descriptor#readme
Project-URL: BugTracker, https://github.com/jet-logic/blob_descriptor/issues
Project-URL: Changelog, https://github.com/jet-logic/blob_descriptor/releases
Keywords: blob,chunk,descriptor,metadata,binary,files
Classifier: Development Status :: 4 - Beta
Classifier: Intended Audience :: Developers
Classifier: Intended Audience :: System Administrators
Classifier: Programming Language :: Python :: 3
Classifier: Operating System :: OS Independent
Classifier: Environment :: Console
Classifier: Topic :: System :: Filesystems
Classifier: Topic :: Utilities
Requires-Python: >=3.8
License-File: LICENSE
Requires-Dist: requests
Provides-Extra: test
Requires-Dist: pytest; extra == "test"
Requires-Dist: pytest-cov; extra == "test"
Provides-Extra: dev
Requires-Dist: black; extra == "dev"
Requires-Dist: flake8; extra == "dev"
Requires-Dist: mypy; extra == "dev"
Requires-Dist: twine; extra == "dev"
Dynamic: license-file
